<?xml version="1.0" encoding="utf-8"?>
<Defs>

  <ThingDef ParentName="BuildingBase">
    <defName>BEWH_ServitorCreator</defName>
    <label>Servitor Creator</label>
    <description>...</description>
    <thingClass>Servitors40k.Building_ServitorCreator</thingClass>
    <containedPawnsSelectable>true</containedPawnsSelectable>
    <passability>Impassable</passability>
    <fillPercent>0.4</fillPercent>
    <castEdgeShadows>true</castEdgeShadows>
    <drawerType>MapMeshAndRealTime</drawerType>
    <tickerType>Normal</tickerType>
    <graphicData>
      <texPath>Things/Building/Servitor/ServitorCreator</texPath>
      <graphicClass>Graphic_Multi</graphicClass>
      <drawSize>(3, 2)</drawSize>
      <shadowData>
        <volume>(1.7, 0.8, 1.7)</volume>
      </shadowData>
    </graphicData>
    <size>(3, 2)</size>
    <canOverlapZones>false</canOverlapZones>
    <hasInteractionCell>true</hasInteractionCell>
    <interactionCellOffset>(0, 0, 2)</interactionCellOffset>
    <defaultPlacingRot>South</defaultPlacingRot>
    <designationCategory>Production</designationCategory>
    <uiOrder>2100</uiOrder>
    <researchPrerequisites>
      <li>BEWH_ServitorCreation</li>
    </researchPrerequisites>
    <statBases>
      <MaxHitPoints>350</MaxHitPoints>
      <WorkToBuild>9000</WorkToBuild>
      <Mass>85</Mass>
      <Flammability>0.5</Flammability>
    </statBases>
    <costList>
      <Steel>300</Steel>
      <Plasteel>30</Plasteel>
      <Gold>5</Gold>
      <ComponentIndustrial>10</ComponentIndustrial>
      <ComponentSpacer>6</ComponentSpacer>
    </costList>
    <constructionSkillPrerequisite>12</constructionSkillPrerequisite>
    <comps>
      <li Class="CompProperties_Power">
        <compClass>CompPowerTrader</compClass>
        <basePowerConsumption>200</basePowerConsumption>
        <idlePowerDraw>50</idlePowerDraw>
      </li>
      <li Class="CompProperties_Flickable" />
      <li Class="CompProperties_Refuelable">
        <fuelConsumptionRate>0.0</fuelConsumptionRate>
        <fuelCapacity>50</fuelCapacity>
        <initialFuelPercent>0</initialFuelPercent>
        <fuelFilter>
          <thingDefs>
            <li>BEWH_ServitorCreationMaterial</li>
          </thingDefs>
        </fuelFilter>
        <showAllowAutoRefuelToggle>true</showAllowAutoRefuelToggle>
      </li>
    </comps>
  </ThingDef>

</Defs>